Metadata-Version: 2.4
Name: llama-index-packs-nebulagraph-query-engine
Version: 0.5.1
Summary: llama-index packs nebulagraph_query_engine integration
Author-email: Your Name <you@example.com>
Maintainer: wenqiglantz
License-Expression: MIT
License-File: LICENSE
Keywords: knowledge graph,nebulagraph,query engine
Requires-Python: <4.0,>=3.9
Requires-Dist: llama-index-core<0.15,>=0.13.0
Requires-Dist: llama-index-graph-stores-nebula<0.6,>=0.5.0
Requires-Dist: llama-index-llms-openai<0.6,>=0.5.0
Requires-Dist: nebula3-python<4,>=3.5.0
